pydorea/__init__.py
pydorea/auth.py
pydorea/client.py
pydorea-0.0.1.dist-info/LICENSE
pydorea-0.0.1.dist-info/METADATA
pydorea-0.0.1.dist-info/WHEEL
pydorea-0.0.1.dist-info/top_level.txt
pydorea-0.0.1.dist-info/RECORD
